{"MapName":"MapWarpTest01","MapWidth":4,"MapHeight":4,"BoundaryWarp":false,"Tiles":[[{"BackgroundImage":"RiverRoadEWNSSample","ObjectListing":["MTOApple","MTOTree"],"Exits":[false,true,true,false],"BattleAllowed":true,"EncounterRate":0.25,"RegionCode":0},{"BackgroundImage":"RiverRoadEWNSSample","ObjectListing":["MTOApple","MTOTree"],"Exits":[false,true,true,true],"BattleAllowed":true,"EncounterRate":0.25,"RegionCode":0},{"BackgroundImage":"RiverRoadEWNSSample","ObjectListing":["MTOApple","MTOTree"],"Exits":[false,true,true,true],"BattleAllowed":true,"EncounterRate":0.25,"RegionCode":0},{"BackgroundImage":"RiverRoadEWNSSample","ObjectListing":["MTOApple","MTOTree","MTODoor00001"],"Exits":[false,true,false,true],"BattleAllowed":true,"EncounterRate":0.25,"RegionCode":0}],[{"BackgroundImage":"RiverRoadSample","ObjectListing":["MTOApple","MTOTree"],"Exits":[true,true,true,false],"BattleAllowed":true,"EncounterRate":0.25,"RegionCode":0},{"BackgroundImage":"FieldPlainsRoadNorthSouthEastWest","ObjectListing":["MTOApple","MTOTree"],"Exits":[true,true,true,true],"BattleAllowed":true,"EncounterRate":0.25,"RegionCode":0},{"BackgroundImage":"RiverRoadSample","ObjectListing":["MTOApple","MTOTree"],"Exits":[true,true,true,true],"BattleAllowed":true,"EncounterRate":0.25,"RegionCode":0},{"BackgroundImage":"FieldPlainsRoadNorthSouthWest","ObjectListing":["MTOApple","MTOTree"],"Exits":[true,true,false,true],"BattleAllowed":true,"EncounterRate":0.25,"RegionCode":0}],[{"BackgroundImage":"FieldPlainsNoRoad","ObjectListing":["MTOApple","MTOTree"],"Exits":[true,true,true,false],"BattleAllowed":true,"EncounterRate":0.25,"RegionCode":0},{"BackgroundImage":"FieldPlainsNoRoad","ObjectListing":["MTOApple","MTOTree"],"Exits":[true,true,true,true],"BattleAllowed":true,"EncounterRate":0.25,"RegionCode":0},{"BackgroundImage":"FieldPlainsNoRoad","ObjectListing":["MTOApple","MTOTree"],"Exits":[true,true,true,true],"BattleAllowed":true,"EncounterRate":0,"RegionCode":0},{"BackgroundImage":"FieldPlainsNoRoad","ObjectListing":["MTOApple","MTOTree"],"Exits":[true,true,false,true],"BattleAllowed":true,"EncounterRate":0,"RegionCode":0}],[{"BackgroundImage":"RiverRoadEWSSSample","ObjectListing":["MTOApple","MTOTree"],"Exits":[true,false,true,false],"BattleAllowed":true,"EncounterRate":0,"RegionCode":0},{"BackgroundImage":"RiverRoadEWSSSample","ObjectListing":["MTOApple","MTOTree"],"Exits":[true,false,true,true],"BattleAllowed":true,"EncounterRate":0,"RegionCode":0},{"BackgroundImage":"RiverRoadEWSSSample","ObjectListing":["MTOApple","MTOTree"],"Exits":[true,false,true,true],"BattleAllowed":true,"EncounterRate":0,"RegionCode":0},{"BackgroundImage":"RiverRoadEWSSSample","ObjectListing":["MTOApple","MTOTree"],"Exits":[true,false,false,true],"BattleAllowed":true,"EncounterRate":0,"RegionCode":0}]]}